PackagePy/Server_Swagger.py
PackagePy/__init__.py
PackagePy/jwtclass.py
PackagePy/queryclass.py
skkwiaaisi-0.0.3.dist-info/METADATA
skkwiaaisi-0.0.3.dist-info/WHEEL
skkwiaaisi-0.0.3.dist-info/top_level.txt
skkwiaaisi-0.0.3.dist-info/RECORD
